{
    "survey_id": "26a7f1d8-18c3-4cc1-a31e-3f3f9a8b960a",
    "survey_name": "Employee Satisfaction with Digital Onboarding Experience Survey",
    "survey_brief": "This survey aims to gather employee feedback on their digital onboarding experience to improve future onboarding processes.",
    "questions": [
        {
            "qid": "Q1",
            "question_text": "How satisfied are you with the overall digital onboarding process?",
            "answer_options": [
                "Very satisfied",
                "Satisfied",
                "Neutral",
                "Dissatisfied",
                "Very dissatisfied"
            ],
            "routing_logic": "Appears for all respondents",
            "client_notes": "Use a 5-point Likert scale to measure satisfaction levels. Ensure the scale is mobile-friendly.",
            "scripter_notes": "Field type: Radio button (single-choice).",
            "script": {
                "question_text": "How satisfied are you with the overall digital onboarding process?",
                "answer_options": [
                    "Very satisfied",
                    "Satisfied",
                    "Neutral",
                    "Dissatisfied",
                    "Very dissatisfied"
                ],
                "type": "SINGLE_CHOICE",
                "routing_logic": "Appears for all respondents"
            }
        },
        {
            "qid": "Q2",
            "question_text": "Which of the following onboarding materials were most helpful? (Select all that apply)",
            "answer_options": [
                "Company culture video",
                "Employee handbook PDF",
                "Interactive training modules",
                "Virtual meet-and-greet sessions",
                "Orientation webinars"
            ],
            "routing_logic": "Appears for all respondents",
            "client_notes": "Multi-choice question; useful for identifying most effective resources.",
            "scripter_notes": "Field type: Checkbox (multi-choice).",
            "script": {
                "question_text": "Which of the following onboarding materials were most helpful? (Select all that apply)",
                "answer_options": [
                    "Company culture video",
                    "Employee handbook PDF",
                    "Interactive training modules",
                    "Virtual meet-and-greet sessions",
                    "Orientation webinars"
                ],
                "type": "MULTI_CHOICE",
                "routing_logic": "Appears for all respondents"
            }
        },
        {
            "qid": "Q3",
            "question_text": "What challenges, if any, did you face during the digital onboarding process?",
            "answer_options": [],
            "routing_logic": "Appears for all respondents",
            "client_notes": "Open-ended question to capture qualitative feedback. Ensure text box is mobile-friendly.",
            "scripter_notes": "Field type: Open text.",
            "script": {
                "question_text": "What challenges, if any, did you face during the digital onboarding process?",
                "answer_options": [],
                "type": "OPEN_TEXT",
                "routing_logic": "Appears for all respondents"
            }
        },
        {
            "qid": "Q4",
            "question_text": "How would you rate the ease of accessing the onboarding portal?",
            "answer_options": [
                "Very easy",
                "Easy",
                "Neutral",
                "Difficult",
                "Very difficult"
            ],
            "routing_logic": "Appears for all respondents",
            "client_notes": "Use a 5-point Likert scale for consistency.",
            "scripter_notes": "Field type: Radio button (single-choice).",
            "script": {
                "question_text": "How would you rate the ease of accessing the onboarding portal?",
                "answer_options": [
                    "Very easy",
                    "Easy",
                    "Neutral",
                    "Difficult",
                    "Very difficult"
                ],
                "type": "SINGLE_CHOICE",
                "routing_logic": "Appears for all respondents"
            }
        },
        {
            "qid": "Q5",
            "question_text": "What improvements would you suggest for the digital onboarding process?",
            "answer_options": [],
            "routing_logic": "Appears for all respondents",
            "client_notes": "Open-ended question for actionable feedback. Encourage detailed responses.",
            "scripter_notes": "Field type: Open text.",
            "script": {
                "question_text": "What improvements would you suggest for the digital onboarding process?",
                "answer_options": [],
                "type": "OPEN_TEXT",
                "routing_logic": "Appears for all respondents"
            }
        }
    ]
}