{
    "survey_id": "48c3a789-5e42-4e3d-bef5-41d00136b5e1",
    "survey_name": "Consumer Preferences for Eco-Friendly Household Cleaning Products Survey",
    "survey_brief": "This survey aims to understand consumer preferences and behaviors regarding the use of eco-friendly household cleaning products, including factors influencing purchase decisions and satisfaction levels.",
    "questions": [
        {
            "qid": "Q1",
            "question_text": "How often do you purchase eco-friendly household cleaning products?",
            "answer_options": [
                "Always",
                "Frequently",
                "Occasionally",
                "Rarely",
                "Never"
            ],
            "routing_logic": "Appears for all respondents.",
            "client_notes": "Use a Likert scale to capture frequency. Ensure the options are mutually exclusive.",
            "scripter_notes": "Field type: Single-choice (radio buttons).",
            "script": {
                "question_text": "How often do you purchase eco-friendly household cleaning products?",
                "answer_options": [
                    "Always",
                    "Frequently",
                    "Occasionally",
                    "Rarely",
                    "Never"
                ],
                "type": "SINGLE_CHOICE",
                "routing_logic": "Appears for all respondents."
            }
        },
        {
            "qid": "Q2",
            "question_text": "What factors most influence your decision to purchase eco-friendly cleaning products? (Select all that apply)",
            "answer_options": [
                "Environmental impact",
                "Health benefits",
                "Product effectiveness",
                "Price",
                "Brand reputation",
                "Packaging sustainability",
                "Other (please specify)"
            ],
            "routing_logic": "Appears for all respondents.",
            "client_notes": "Allow multiple selections to capture diverse influences.",
            "scripter_notes": "Field type: Multi-choice (checkboxes). Include an 'Other' option with a text field.",
            "script": {
                "question_text": "What factors most influence your decision to purchase eco-friendly cleaning products? (Select all that apply)",
                "answer_options": [
                    "Environmental impact",
                    "Health benefits",
                    "Product effectiveness",
                    "Price",
                    "Brand reputation",
                    "Packaging sustainability",
                    "Other (please specify)"
                ],
                "type": "MULTI_CHOICE",
                "routing_logic": "Appears for all respondents."
            }
        },
        {
            "qid": "Q3",
            "question_text": "Please describe any challenges you face when using eco-friendly cleaning products.",
            "answer_options": [],
            "routing_logic": "Appears for respondents who selected 'Occasionally', 'Frequently', or 'Always' in Q1.",
            "client_notes": "Open-ended question to gather qualitative insights. Ensure the response box is large enough for detailed answers.",
            "scripter_notes": "Field type: Open-text.",
            "script": {
                "question_text": "Please describe any challenges you face when using eco-friendly cleaning products.",
                "answer_options": [],
                "type": "OPEN_TEXT",
                "routing_logic": "Appears for respondents who selected 'Occasionally', 'Frequently', or 'Always' in Q1."
            }
        },
        {
            "qid": "Q4",
            "question_text": "How satisfied are you with the effectiveness of eco-friendly cleaning products compared to traditional ones?",
            "answer_options": [
                "Very satisfied",
                "Satisfied",
                "Neutral",
                "Dissatisfied",
                "Very dissatisfied"
            ],
            "routing_logic": "Appears for respondents who selected 'Occasionally', 'Frequently', or 'Always' in Q1.",
            "client_notes": "Use a Likert scale to measure satisfaction levels.",
            "scripter_notes": "Field type: Single-choice (radio buttons).",
            "script": {
                "question_text": "How satisfied are you with the effectiveness of eco-friendly cleaning products compared to traditional ones?",
                "answer_options": [
                    "Very satisfied",
                    "Satisfied",
                    "Neutral",
                    "Dissatisfied",
                    "Very dissatisfied"
                ],
                "type": "SINGLE_CHOICE",
                "routing_logic": "Appears for respondents who selected 'Occasionally', 'Frequently', or 'Always' in Q1."
            }
        },
        {
            "qid": "Q5",
            "question_text": "Would you be willing to pay a premium for eco-friendly cleaning products if they were proven to be more effective than traditional products?",
            "answer_options": [
                "Yes",
                "No",
                "Maybe, depending on the price difference"
            ],
            "routing_logic": "Appears for all respondents.",
            "client_notes": "Capture willingness to pay with clear options.",
            "scripter_notes": "Field type: Single-choice (radio buttons).",
            "script": {
                "question_text": "Would you be willing to pay a premium for eco-friendly cleaning products if they were proven to be more effective than traditional products?",
                "answer_options": [
                    "Yes",
                    "No",
                    "Maybe, depending on the price difference"
                ],
                "type": "SINGLE_CHOICE",
                "routing_logic": "Appears for all respondents."
            }
        }
    ]
}