{
    "survey_id": "60f567cf-e9bb-4fcd-855d-ba2cf221bd88",
    "survey_name": "Urban Bike Sharing Program Satisfaction Survey",
    "survey_brief": "This survey aims to gather feedback from users of the city's bike-sharing program to assess satisfaction levels and identify areas for improvement.",
    "questions": [
        {
            "qid": "Q1",
            "question_text": "How often do you use the city's bike-sharing program?",
            "answer_options": [
                "Daily",
                "Weekly",
                "Monthly",
                "Occasionally",
                "First-time user"
            ],
            "routing_logic": "All respondents",
            "client_notes": "Use a single-choice radio button format for clarity.",
            "scripter_notes": "Field type: radio button (SINGLE_CHOICE).",
            "script": {
                "question_text": "How often do you use the city's bike-sharing program?",
                "answer_options": [
                    "Daily",
                    "Weekly",
                    "Monthly",
                    "Occasionally",
                    "First-time user"
                ],
                "type": "SINGLE_CHOICE",
                "routing_logic": "All respondents"
            }
        },
        {
            "qid": "Q2",
            "question_text": "What are the primary reasons you use the bike-sharing program? (Select all that apply)",
            "answer_options": [
                "Convenience",
                "Cost savings",
                "Health and fitness",
                "Environmental concerns",
                "Avoiding traffic",
                "Other (please specify)"
            ],
            "routing_logic": "All respondents",
            "client_notes": "Use a multi-choice checkbox format and include an 'Other' option with a text field.",
            "scripter_notes": "Field type: checkbox (MULTI_CHOICE) with optional open-text for 'Other'.",
            "script": {
                "question_text": "What are the primary reasons you use the bike-sharing program? (Select all that apply)",
                "answer_options": [
                    "Convenience",
                    "Cost savings",
                    "Health and fitness",
                    "Environmental concerns",
                    "Avoiding traffic",
                    "Other (please specify)"
                ],
                "type": "MULTI_CHOICE",
                "routing_logic": "All respondents"
            }
        },
        {
            "qid": "Q3",
            "question_text": "How satisfied are you with the availability of bikes at your usual pickup locations?",
            "answer_options": [
                "Very satisfied",
                "Satisfied",
                "Neutral",
                "Dissatisfied",
                "Very dissatisfied"
            ],
            "routing_logic": "All respondents",
            "client_notes": "Use a 5-point Likert scale for consistency.",
            "scripter_notes": "Field type: radio button (SINGLE_CHOICE).",
            "script": {
                "question_text": "How satisfied are you with the availability of bikes at your usual pickup locations?",
                "answer_options": [
                    "Very satisfied",
                    "Satisfied",
                    "Neutral",
                    "Dissatisfied",
                    "Very dissatisfied"
                ],
                "type": "SINGLE_CHOICE",
                "routing_logic": "All respondents"
            }
        },
        {
            "qid": "Q4",
            "question_text": "What improvements would you suggest for the bike-sharing program?",
            "answer_options": [],
            "routing_logic": "All respondents",
            "client_notes": "Open-ended question to capture qualitative feedback.",
            "scripter_notes": "Field type: open text (OPEN_TEXT).",
            "script": {
                "question_text": "What improvements would you suggest for the bike-sharing program?",
                "answer_options": [],
                "type": "OPEN_TEXT",
                "routing_logic": "All respondents"
            }
        },
        {
            "qid": "Q5",
            "question_text": "Would you recommend the bike-sharing program to others?",
            "answer_options": [
                "Yes",
                "No",
                "Maybe"
            ],
            "routing_logic": "All respondents",
            "client_notes": "Simple yes/no/maybe format for quick response.",
            "scripter_notes": "Field type: radio button (SINGLE_CHOICE).",
            "script": {
                "question_text": "Would you recommend the bike-sharing program to others?",
                "answer_options": [
                    "Yes",
                    "No",
                    "Maybe"
                ],
                "type": "SINGLE_CHOICE",
                "routing_logic": "All respondents"
            }
        }
    ]
}