{
    "survey_id": "8ca4ac0b-be63-4718-981d-6b47075cbaf7",
    "survey_name": "Local Farmers' Market Vendor Satisfaction Survey",
    "survey_brief": "This survey aims to gather feedback from vendors at local farmers' markets to understand their satisfaction levels, challenges, and suggestions for improvement.",
    "questions": [
        {
            "qid": "Q1",
            "question_text": "How satisfied are you with your overall experience as a vendor at this farmers' market?",
            "answer_options": [
                "Very satisfied",
                "Somewhat satisfied",
                "Neutral",
                "Somewhat dissatisfied",
                "Very dissatisfied"
            ],
            "routing_logic": "This question appears for all respondents.",
            "client_notes": "Use a 5-point Likert scale for consistent measurement. Ensure the question is mobile-friendly.",
            "scripter_notes": "Use radio buttons for single-choice selection.",
            "script": {
                "question_text": "How satisfied are you with your overall experience as a vendor at this farmers' market?",
                "answer_options": [
                    "Very satisfied",
                    "Somewhat satisfied",
                    "Neutral",
                    "Somewhat dissatisfied",
                    "Very dissatisfied"
                ],
                "type": "SINGLE_CHOICE",
                "routing_logic": "This question appears for all respondents."
            }
        },
        {
            "qid": "Q2",
            "question_text": "Which of the following facilities or services provided by the market do you find most useful? (Select all that apply)",
            "answer_options": [
                "Customer traffic and footfall",
                "Booth setup and space allocation",
                "Marketing and promotional support",
                "Payment processing options",
                "Restroom facilities",
                "Parking availability",
                "Other (please specify)"
            ],
            "routing_logic": "This question appears for all respondents.",
            "client_notes": "Allow multiple selections. Include an 'Other' option for additional feedback.",
            "scripter_notes": "Use checkboxes for multi-choice selection. Include a text field for 'Other' if selected.",
            "script": {
                "question_text": "Which of the following facilities or services provided by the market do you find most useful? (Select all that apply)",
                "answer_options": [
                    "Customer traffic and footfall",
                    "Booth setup and space allocation",
                    "Marketing and promotional support",
                    "Payment processing options",
                    "Restroom facilities",
                    "Parking availability",
                    "Other (please specify)"
                ],
                "type": "MULTI_CHOICE",
                "routing_logic": "This question appears for all respondents."
            }
        },
        {
            "qid": "Q3",
            "question_text": "What challenges have you faced as a vendor at this farmers' market?",
            "answer_options": [],
            "routing_logic": "This question appears for all respondents.",
            "client_notes": "Open-ended question to capture detailed feedback. Encourage vendors to share specific issues.",
            "scripter_notes": "Use a text input field for open-ended responses.",
            "script": {
                "question_text": "What challenges have you faced as a vendor at this farmers' market?",
                "answer_options": [],
                "type": "OPEN_TEXT",
                "routing_logic": "This question appears for all respondents."
            }
        },
        {
            "qid": "Q4",
            "question_text": "How likely are you to continue vending at this farmers' market in the next season?",
            "answer_options": [
                "Extremely likely",
                "Somewhat likely",
                "Neutral",
                "Somewhat unlikely",
                "Extremely unlikely"
            ],
            "routing_logic": "This question appears for all respondents.",
            "client_notes": "Use a 5-point Likert scale to measure likelihood. Ensure clarity in response options.",
            "scripter_notes": "Use radio buttons for single-choice selection.",
            "script": {
                "question_text": "How likely are you to continue vending at this farmers' market in the next season?",
                "answer_options": [
                    "Extremely likely",
                    "Somewhat likely",
                    "Neutral",
                    "Somewhat unlikely",
                    "Extremely unlikely"
                ],
                "type": "SINGLE_CHOICE",
                "routing_logic": "This question appears for all respondents."
            }
        },
        {
            "qid": "Q5",
            "question_text": "What improvements would you suggest to enhance the farmers' market experience for vendors?",
            "answer_options": [],
            "routing_logic": "This question appears for all respondents.",
            "client_notes": "Open-ended question to gather actionable suggestions. Keep the text field sizable for detailed responses.",
            "scripter_notes": "Use a text area input field for longer open-ended responses.",
            "script": {
                "question_text": "What improvements would you suggest to enhance the farmers' market experience for vendors?",
                "answer_options": [],
                "type": "OPEN_TEXT",
                "routing_logic": "This question appears for all respondents."
            }
        }
    ]
}