{
    "survey_id": "b70cbac0-b929-4930-826a-90120a219613",
    "survey_name": "Freelance Platform User Experience Survey",
    "survey_brief": "This survey aims to gather feedback from freelancers about their experience using the platform to help improve services and user satisfaction.",
    "questions": [
        {
            "qid": "Q1",
            "question_text": "How often do you use the freelance platform?",
            "answer_options": [
                "Daily",
                "Weekly",
                "Monthly",
                "Less than once a month"
            ],
            "routing_logic": "Always shown",
            "client_notes": "Use a radio button for single-choice selection. Ensure the options cover the frequency spectrum.",
            "scripter_notes": "Field type: Radio button (SINGLE_CHOICE)",
            "script": {
                "question_text": "How often do you use the freelance platform?",
                "answer_options": [
                    "Daily",
                    "Weekly",
                    "Monthly",
                    "Less than once a month"
                ],
                "type": "SINGLE_CHOICE",
                "routing_logic": "Always shown"
            }
        },
        {
            "qid": "Q2",
            "question_text": "What type of freelance work do you primarily seek on the platform?",
            "answer_options": [
                "Writing & Editing",
                "Graphic Design",
                "Web Development",
                "Marketing",
                "Data Analysis",
                "Other (please specify)"
            ],
            "routing_logic": "Always shown",
            "client_notes": "Allow multiple selections with a checkbox option for 'Other' to capture niche categories.",
            "scripter_notes": "Field type: Checkbox (MULTI_CHOICE) with an optional open-text field for 'Other'.",
            "script": {
                "question_text": "What type of freelance work do you primarily seek on the platform?",
                "answer_options": [
                    "Writing & Editing",
                    "Graphic Design",
                    "Web Development",
                    "Marketing",
                    "Data Analysis",
                    "Other (please specify)"
                ],
                "type": "MULTI_CHOICE",
                "routing_logic": "Always shown"
            }
        },
        {
            "qid": "Q3",
            "question_text": "On a scale of 1 to 5, how satisfied are you with the platform's job matching algorithm? (1 = Very dissatisfied, 5 = Very satisfied)",
            "answer_options": [
                "1",
                "2",
                "3",
                "4",
                "5"
            ],
            "routing_logic": "Always shown",
            "client_notes": "Use a Likert scale for clarity. Ensure the scale is labeled appropriately.",
            "scripter_notes": "Field type: Radio button (SINGLE_CHOICE) with a 5-point scale.",
            "script": {
                "question_text": "On a scale of 1 to 5, how satisfied are you with the platform's job matching algorithm? (1 = Very dissatisfied, 5 = Very satisfied)",
                "answer_options": [
                    "1",
                    "2",
                    "3",
                    "4",
                    "5"
                ],
                "type": "SINGLE_CHOICE",
                "routing_logic": "Always shown"
            }
        },
        {
            "qid": "Q4",
            "question_text": "What features do you find most valuable on the platform? (Select all that apply)",
            "answer_options": [
                "Job search filters",
                "Client rating system",
                "Secure payment system",
                "Messaging tools",
                "Portfolio display",
                "Other (please specify)"
            ],
            "routing_logic": "Always shown",
            "client_notes": "Multiple selections allowed. Include an 'Other' option for additional feedback.",
            "scripter_notes": "Field type: Checkbox (MULTI_CHOICE) with an optional open-text field for 'Other'.",
            "script": {
                "question_text": "What features do you find most valuable on the platform? (Select all that apply)",
                "answer_options": [
                    "Job search filters",
                    "Client rating system",
                    "Secure payment system",
                    "Messaging tools",
                    "Portfolio display",
                    "Other (please specify)"
                ],
                "type": "MULTI_CHOICE",
                "routing_logic": "Always shown"
            }
        },
        {
            "qid": "Q5",
            "question_text": "What challenges have you faced while using the platform?",
            "answer_options": [],
            "routing_logic": "Always shown",
            "client_notes": "Open-ended question to capture detailed feedback. Consider limiting response length to 500 characters.",
            "scripter_notes": "Field type: Open text (OPEN_TEXT) with a character limit.",
            "script": {
                "question_text": "What challenges have you faced while using the platform?",
                "answer_options": [],
                "type": "OPEN_TEXT",
                "routing_logic": "Always shown"
            }
        },
        {
            "qid": "Q6",
            "question_text": "How likely are you to recommend the platform to other freelancers? (1 = Not at all likely, 10 = Extremely likely)",
            "answer_options": [
                "1",
                "2",
                "3",
                "4",
                "5",
                "6",
                "7",
                "8",
                "9",
                "10"
            ],
            "routing_logic": "Always shown",
            "client_notes": "Use a 10-point scale for nuanced feedback. Ensure the scale endpoints are clearly labeled.",
            "scripter_notes": "Field type: Radio button (SINGLE_CHOICE) with a 10-point scale.",
            "script": {
                "question_text": "How likely are you to recommend the platform to other freelancers? (1 = Not at all likely, 10 = Extremely likely)",
                "answer_options": [
                    "1",
                    "2",
                    "3",
                    "4",
                    "5",
                    "6",
                    "7",
                    "8",
                    "9",
                    "10"
                ],
                "type": "SINGLE_CHOICE",
                "routing_logic": "Always shown"
            }
        },
        {
            "qid": "Q7",
            "question_text": "How would you rate the platform's customer support responsiveness?",
            "answer_options": [
                "Poor",
                "Fair",
                "Good",
                "Very Good",
                "Excellent"
            ],
            "routing_logic": "Always shown",
            "client_notes": "Use a standard 5-point qualitative scale for clarity.",
            "scripter_notes": "Field type: Radio button (SINGLE_CHOICE).",
            "script": {
                "question_text": "How would you rate the platform's customer support responsiveness?",
                "answer_options": [
                    "Poor",
                    "Fair",
                    "Good",
                    "Very Good",
                    "Excellent"
                ],
                "type": "SINGLE_CHOICE",
                "routing_logic": "Always shown"
            }
        },
        {
            "qid": "Q8",
            "question_text": "Which of the following improvements would most enhance your experience on the platform? (Select up to 3)",
            "answer_options": [
                "Better job matching algorithms",
                "Lower service fees",
                "More transparent client reviews",
                "Enhanced dispute resolution",
                "Improved mobile app functionality",
                "Other (please specify)"
            ],
            "routing_logic": "Always shown",
            "client_notes": "Allow selection of up to 3 options. Include an 'Other' field for additional suggestions.",
            "scripter_notes": "Field type: Checkbox (MULTI_CHOICE) with a max selection of 3 and an optional open-text field for 'Other'.",
            "script": {
                "question_text": "Which of the following improvements would most enhance your experience on the platform? (Select up to 3)",
                "answer_options": [
                    "Better job matching algorithms",
                    "Lower service fees",
                    "More transparent client reviews",
                    "Enhanced dispute resolution",
                    "Improved mobile app functionality",
                    "Other (please specify)"
                ],
                "type": "MULTI_CHOICE",
                "routing_logic": "Always shown"
            }
        },
        {
            "qid": "Q9",
            "question_text": "How important is the platform's fee structure in your decision to accept a job?",
            "answer_options": [
                "Not important at all",
                "Slightly important",
                "Moderately important",
                "Very important",
                "Extremely important"
            ],
            "routing_logic": "Always shown",
            "client_notes": "Use a 5-point Likert scale to measure importance.",
            "scripter_notes": "Field type: Radio button (SINGLE_CHOICE).",
            "script": {
                "question_text": "How important is the platform's fee structure in your decision to accept a job?",
                "answer_options": [
                    "Not important at all",
                    "Slightly important",
                    "Moderately important",
                    "Very important",
                    "Extremely important"
                ],
                "type": "SINGLE_CHOICE",
                "routing_logic": "Always shown"
            }
        },
        {
            "qid": "Q10",
            "question_text": "Do you have any additional comments or suggestions for improving the platform?",
            "answer_options": [],
            "routing_logic": "Always shown",
            "client_notes": "Open-ended question to capture final thoughts. Limit response to 1000 characters.",
            "scripter_notes": "Field type: Open text (OPEN_TEXT) with a character limit.",
            "script": {
                "question_text": "Do you have any additional comments or suggestions for improving the platform?",
                "answer_options": [],
                "type": "OPEN_TEXT",
                "routing_logic": "Always shown"
            }
        }
    ]
}