{
    "survey_id": "e7c02233-b9da-4b24-a8a0-b724c8f0ac0d",
    "survey_name": "Customer Satisfaction with Bicycle Sharing Programs Survey",
    "survey_brief": "This survey aims to gather feedback from users of urban bicycle sharing programs to evaluate satisfaction levels, identify pain points, and improve service offerings.",
    "questions": [
        {
            "qid": "Q1",
            "question_text": "How frequently do you use bicycle sharing programs in your city?",
            "answer_options": [
                "Daily",
                "Weekly",
                "Monthly",
                "Rarely",
                "First-time user"
            ],
            "routing_logic": "All respondents",
            "client_notes": "Use a single-choice radio button for clear frequency measurement. Mobile-friendly design recommended.",
            "scripter_notes": "Field type: SINGLE_CHOICE (radio buttons)",
            "script": {
                "question_text": "How frequently do you use bicycle sharing programs in your city?",
                "answer_options": [
                    "Daily",
                    "Weekly",
                    "Monthly",
                    "Rarely",
                    "First-time user"
                ],
                "type": "SINGLE_CHOICE",
                "routing_logic": "All respondents"
            }
        },
        {
            "qid": "Q2",
            "question_text": "What factors influence your decision to use a bicycle sharing program? (Select all that apply)",
            "answer_options": [
                "Convenience",
                "Cost-effectiveness",
                "Environmental concerns",
                "Health benefits",
                "Lack of personal bicycle",
                "Traffic congestion avoidance"
            ],
            "routing_logic": "All respondents",
            "client_notes": "Multi-choice checkbox format allows for multiple selections. Randomize option order to reduce bias.",
            "scripter_notes": "Field type: MULTI_CHOICE (checkboxes)",
            "script": {
                "question_text": "What factors influence your decision to use a bicycle sharing program? (Select all that apply)",
                "answer_options": [
                    "Convenience",
                    "Cost-effectiveness",
                    "Environmental concerns",
                    "Health benefits",
                    "Lack of personal bicycle",
                    "Traffic congestion avoidance"
                ],
                "type": "MULTI_CHOICE",
                "routing_logic": "All respondents"
            }
        },
        {
            "qid": "Q3",
            "question_text": "On a scale of 1-5, how satisfied are you with the availability of bicycles at your preferred locations?",
            "answer_options": [
                "1 - Very dissatisfied",
                "2",
                "3 - Neutral",
                "4",
                "5 - Very satisfied"
            ],
            "routing_logic": "All respondents",
            "client_notes": "5-point Likert scale with labeled endpoints. Include visual analog scale if possible.",
            "scripter_notes": "Field type: SINGLE_CHOICE (radio buttons with scale display)",
            "script": {
                "question_text": "On a scale of 1-5, how satisfied are you with the availability of bicycles at your preferred locations?",
                "answer_options": [
                    "1 - Very dissatisfied",
                    "2",
                    "3 - Neutral",
                    "4",
                    "5 - Very satisfied"
                ],
                "type": "SINGLE_CHOICE",
                "routing_logic": "All respondents"
            }
        },
        {
            "qid": "Q4",
            "question_text": "What improvements would you suggest for the bicycle sharing program in your city?",
            "answer_options": [],
            "routing_logic": "All respondents",
            "client_notes": "Open-ended question to capture qualitative feedback. Limit response to 250 characters.",
            "scripter_notes": "Field type: OPEN_TEXT (text input box with character limit)",
            "script": {
                "question_text": "What improvements would you suggest for the bicycle sharing program in your city?",
                "answer_options": [],
                "type": "OPEN_TEXT",
                "routing_logic": "All respondents"
            }
        },
        {
            "qid": "Q5",
            "question_text": "Have you experienced any technical issues with the bicycle sharing mobile app?",
            "answer_options": [
                "Yes, frequently",
                "Yes, occasionally",
                "No, never",
                "I don't use the mobile app"
            ],
            "routing_logic": "All respondents",
            "client_notes": "Include an option for non-app users to prevent forced responses. Mobile-first design crucial.",
            "scripter_notes": "Field type: SINGLE_CHOICE (radio buttons)",
            "script": {
                "question_text": "Have you experienced any technical issues with the bicycle sharing mobile app?",
                "answer_options": [
                    "Yes, frequently",
                    "Yes, occasionally",
                    "No, never",
                    "I don't use the mobile app"
                ],
                "type": "SINGLE_CHOICE",
                "routing_logic": "All respondents"
            }
        }
    ]
}